babyapi/__init__.py
babyapi/client.py
babyapi/errors.py
babyapi/resources.py
babyapi/streaming.py
babyapi-0.1.0.dist-info/METADATA
babyapi-0.1.0.dist-info/WHEEL
babyapi-0.1.0.dist-info/RECORD
