Metadata-Version: 2.4
Name: babyapi
Version: 0.1.0
Summary: BabyAPI client.
Project-URL: Homepage, https://babyapi.org
Project-URL: Repository, https://github.com/babyapi-org/babyapi-python
Project-URL: Issues, https://github.com/babyapi-org/babyapi-python/issues
Author-email: BabyAPI <support@babyapi.org>
License: MIT
Keywords: babyapi,chat-completions,completions,llm,openai,vllm
Classifier: License :: OSI Approved :: MIT License
Classifier: Operating System :: OS Independent
Classifier: Programming Language :: Python :: 3
Classifier: Programming Language :: Python :: 3 :: Only
Requires-Python: >=3.9
Requires-Dist: httpx>=0.27.0
